pdkmaster/io/spice/__init__.py
pdkmaster/io/spice/_util.py
pdkmaster/io/spice/doit.py
pdkmaster/io/spice/pyspice.py
pdkmaster/io/spice/spice_.py
pdkmaster/io/spice/typing.py
pdkmaster_io_spice-0.1.0.dist-info/METADATA
pdkmaster_io_spice-0.1.0.dist-info/WHEEL
pdkmaster_io_spice-0.1.0.dist-info/entry_points.txt
pdkmaster_io_spice-0.1.0.dist-info/licenses/LICENSE.md
pdkmaster_io_spice-0.1.0.dist-info/RECORD
