Metadata-Version: 2.1
Name: pdkmaster-io-spice
Version: 0.1.0
Summary: PDKMaster integration with SPICE simulators
Author-Email: Staf Verhaegen <staf@fibraservi.eu>
License: AGPL-3.0-or-later OR GPL-2.0-or-later OR CERN-OHL-S-2.0+ OR Apache-2.0
Requires-Python: >=3.8
Requires-Dist: PDKMaster~=0.12.0
Requires-Dist: PySpice>=1.5
